verilog/finaldff.v
module dff (
    input wire clk,
    input wire d,
    output reg q
);
    always @(posedge clk) begin
        q <= d;
    end
endmodule

module dff_tb;
    reg clk;
    reg d;
    wire q;

    dff uut (
        .clk(clk),
        .d(d),
        .q(q)
    );

    initial begin
        $dumpfile("dff.vcd");
        $dumpvars(0, dff_tb);
        clk = 0;
        forever #5 clk = ~clk; 
    end

    initial begin
        d = 0;

        #10 d = 1;
        #15 d = 0;
        #10 d = 1;
        #10 d = 0;
        #10 d = 1;

        #10 $finish;
    end

    initial begin
        $monitor("At time %t, d = %b, q = %b", $time, d, q);
    end
endmodule

verilog/dff.vcd
$date
	Tue Dec  3 04:08:49 2024
$end
$version
	Icarus Verilog
$end
$timescale
	1s
$end
$scope module dff_tb $end
$var wire 1 ! q $end
$var reg 1 " clk $end
$var reg 1 # d $end
$scope module uut $end
$var wire 1 " clk $end
$var wire 1 # d $end
$var reg 1 ! q $end
$upscope $end
$upscope $end
$enddefinitions $end
#0
$dumpvars
0#
0"
x!
$end
#5
0!
1"
#10
0"
1#
#15
1!
1"
#20
0"
#25
0!
1"
0#
#30
0"
#35
1!
1"
1#
#40
0"
#45
0!
1"
0#
#50
0"
#55
1!
1"
1#
